aniwrap/__init__.py
aniwrap/client.py
aniwrap/endpoints.py
aniwrap/enums/__init__.py
aniwrap/enums/anime.py
aniwrap/enums/base.py
aniwrap/enums/common.py
aniwrap/enums/http.py
aniwrap/enums/manga.py
aniwrap/enums/user.py
aniwrap/models/__init__.py
aniwrap/models/anime.py
aniwrap/models/base.py
aniwrap/models/common.py
aniwrap/models/forum.py
aniwrap/models/http.py
aniwrap/models/manga.py
aniwrap/models/route.py
aniwrap/models/user.py
aniwrap/py.typed
aniwrap/result.py
aniwrap/serializer.py
aniwrap/services/__init__.py
aniwrap/services/anime.py
aniwrap/services/base.py
aniwrap/services/forum.py
aniwrap/services/http.py
aniwrap/services/manga.py
aniwrap/services/user.py
aniwrap-1.0.1.dist-info/LICENSE
aniwrap-1.0.1.dist-info/METADATA
aniwrap-1.0.1.dist-info/WHEEL
aniwrap-1.0.1.dist-info/RECORD
