Metadata-Version: 2.1
Name: aniwrap
Version: 1.0.1
Summary: An Asynchronous API wrapper for My Anime List API.
Home-page: https://github.com/thevenuz/aniwrap.py
License: MIT
Author: thevenuz
Requires-Python: >=3.10
Classifier: License :: OSI Approved :: MIT License
Classifier: Programming Language :: Python :: 3
Classifier: Programming Language :: Python :: 3.10
Classifier: Programming Language :: Python :: 3.11
Requires-Dist: aiohttp (>=3.8.4)
Requires-Dist: attrs (>=22)
Project-URL: Documentation, https://thevenuz.github.io/aniwrap.py/
Project-URL: Repository, https://github.com/thevenuz/aniwrap.py
